tfds_korean/__init__.py
tfds_korean/build_catalog.py
tfds_korean/klue_dp/__init__.py
tfds_korean/klue_dp/checksums.tsv
tfds_korean/klue_dp/klue_dp.py
tfds_korean/klue_dp/klue_dp_test.py
tfds_korean/klue_dst/__init__.py
tfds_korean/klue_dst/checksums.tsv
tfds_korean/klue_dst/klue_dst.py
tfds_korean/klue_dst/klue_dst_test.py
tfds_korean/klue_mrc/__init__.py
tfds_korean/klue_mrc/checksums.tsv
tfds_korean/klue_mrc/klue_mrc.py
tfds_korean/klue_mrc/klue_mrc_test.py
tfds_korean/klue_ner/__init__.py
tfds_korean/klue_ner/checksums.tsv
tfds_korean/klue_ner/klue_ner.py
tfds_korean/klue_ner/klue_ner_test.py
tfds_korean/klue_nli/__init__.py
tfds_korean/klue_nli/checksums.tsv
tfds_korean/klue_nli/klue_nli.py
tfds_korean/klue_nli/klue_nli_test.py
tfds_korean/klue_re/__init__.py
tfds_korean/klue_re/checksums.tsv
tfds_korean/klue_re/klue_re.py
tfds_korean/klue_re/klue_re_test.py
tfds_korean/klue_sts/__init__.py
tfds_korean/klue_sts/checksums.tsv
tfds_korean/klue_sts/klue_sts.py
tfds_korean/klue_sts/klue_sts_test.py
tfds_korean/klue_tc/__init__.py
tfds_korean/klue_tc/checksums.tsv
tfds_korean/klue_tc/klue_tc.py
tfds_korean/klue_tc/klue_tc_test.py
tfds_korean/kmounlp_ner/__init__.py
tfds_korean/kmounlp_ner/checksums.tsv
tfds_korean/kmounlp_ner/filelist.txt
tfds_korean/kmounlp_ner/kmounlp_ner.py
tfds_korean/kmounlp_ner/kmounlp_ner_test.py
tfds_korean/korean_chatbot_qa_data/__init__.py
tfds_korean/korean_chatbot_qa_data/checksums.tsv
tfds_korean/korean_chatbot_qa_data/korean_chatbot_qa_data.py
tfds_korean/korean_chatbot_qa_data/korean_chatbot_qa_data_test.py
tfds_korean/korean_hate_speech/__init__.py
tfds_korean/korean_hate_speech/checksums.tsv
tfds_korean/korean_hate_speech/korean_hate_speech.py
tfds_korean/korean_hate_speech/korean_hate_speech_test.py
tfds_korean/korean_parallel_corpora/__init__.py
tfds_korean/korean_parallel_corpora/checksums.tsv
tfds_korean/korean_parallel_corpora/korean_parallel_corpora.py
tfds_korean/korean_parallel_corpora/korean_parallel_corpora_test.py
tfds_korean-0.4.0.dist-info/LICENSE
tfds_korean-0.4.0.dist-info/METADATA
tfds_korean-0.4.0.dist-info/WHEEL
tfds_korean-0.4.0.dist-info/top_level.txt
tfds_korean-0.4.0.dist-info/RECORD
