Metadata-Version: 2.1
Name: tfds-korean
Version: 0.4.0
Summary: A collection of Korean Text Datasets ready to use using Tensorflow-Datasets.
Home-page: https://github.com/jeongukjae/tfds-korean
Author: Ukjae Jeong
Author-email: jeongukjae@gmail.com
License: UNKNOWN
Keywords: tensorflow,machine learning,dataset
Platform: UNKNOWN
Classifier: Development Status :: 3 - Alpha
Classifier: Intended Audience :: Developers
Classifier: Intended Audience :: Science/Research
Classifier: License :: OSI Approved :: Apache Software License
Classifier: Programming Language :: Python :: 3
Classifier: Programming Language :: Python :: 3 :: Only
Classifier: Topic :: Scientific/Engineering :: Artificial Intelligence
Requires-Python: >=3.6
Requires-Dist: tensorflow-datasets (>=4.2)
Requires-Dist: tensorflow (>=2.1)
